dophon/__init__.py
dophon/annotation/__init__.py
dophon/annotation/AutoWired.py
dophon/annotation/description/__init__.py
dophon/annotation/description/describe.py
dophon/annotation/request/__init__.py
dophon/annotation/request/param_adapter/__init__.py
dophon/annotation/request/param_adapter/handler.py
dophon/annotation/response/__init__.py
dophon/annotation/side_pkg.py
dophon/boot.py
dophon/cluster_boot.py
dophon/docker_boot.py
dophon/errors/ParamErrors.py
dophon/pre_boot.py
dophon/tools/__init__.py
dophon/tools/dynamic_import.py
dophon/tools/framework_const/__init__.py
dophon/tools/framework_const/error_info_type.py
dophon/tools/framework_const/objs.py
dophon/tools/framework_const/self_result.py
dophon/tools/gc/__init__.py
dophon/tools/sys_utils.py
dophon/web_templates/css.py
dophon/web_templates/javascript.py
dophon/webboot.py
dophon-1.3.6.post10.dist-info/LICENSE
dophon-1.3.6.post10.dist-info/WHEEL
dophon-1.3.6.post10.dist-info/METADATA
dophon-1.3.6.post10.dist-info/RECORD
