Metadata-Version: 2.1
Name: dophon
Version: 1.3.6.post10
Summary: dophon web framework like springboot
License: Apache 2.0
Keywords: web,framework,dophon
Author: CallMeE
Author-email: ealohu@163.com
Requires-Python: >=3.6,<4.0
Classifier: License :: Other/Proprietary License
Classifier: Programming Language :: Python :: 3
Classifier: Programming Language :: Python :: 3.6
Classifier: Programming Language :: Python :: 3.7
Classifier: Programming Language :: Python :: 3.8
Classifier: Programming Language :: Python :: 3.9
Requires-Dist: dophon-logger
Requires-Dist: dophon-manager
Requires-Dist: dophon-properties
Requires-Dist: flask
Requires-Dist: tornado
Requires-Dist: tqdm
Requires-Dist: urllib3
Requires-Dist: xmltodict (>=0.12.0,<0.13.0)
